horus_analytics/__init__.py
horus_camera/__init__.py
horus_db/__init__.py
horus_geometries/__init__.py
horus_geopandas/__init__.py
horus_gis/__init__.py
horus_media/__init__.py
horus_media_examples/__init__.py
horus_media_examples/clustering_analytics.py
horus_media_examples/example_strategy.py
horus_media_examples/export_orthographic.py
horus_media_examples/export_spherical.py
horus_media_examples/export_time_interval.py
horus_media_examples/geosuite_database_info.py
horus_media_examples/recordings_tool.py
horus_media_examples/single_measurement_clustering.py
horus_media_examples/snapshots.py
horus_media_examples/spherical_camera.py
horus_media_examples/spherical_camera_single_measurement.py
horus_media_examples/spherical_camera_single_measurement_reconstruction.py
horus_media_examples/spherical_camera_snapshot.py
horus_media_examples/test_tool.py
horus_media_examples/triangulate_spherical_camera_single_measurement_clusters.py
horus_media_examples/util.py
horus_spatialite/__init__.py
horus_media_client-0.9.7.dist-info/LICENSE.txt
horus_media_client-0.9.7.dist-info/METADATA
horus_media_client-0.9.7.dist-info/WHEEL
horus_media_client-0.9.7.dist-info/top_level.txt
horus_media_client-0.9.7.dist-info/RECORD
