Metadata-Version: 2.1
Name: horus-media-client
Version: 0.9.7
Summary: Horus Media Server Client
Home-page: https://github.com/horus-view-and-explore/horus-media-client
Author: Horus View and Explore B.V.
Author-email: info@horus.nu
License: MIT
Classifier: Programming Language :: Python :: 3.6
Classifier: Operating System :: OS Independent
Classifier: License :: OSI Approved :: MIT License
Requires-Python: >=3.6, <4
License-File: LICENSE.txt
Requires-Dist: psycopg2 >=2.8.4
Requires-Dist: numpy >=1.17.4
Requires-Dist: pymap3d >=2.1.0
Requires-Dist: pillow >=6.2.1
Requires-Dist: scipy >=1.3.3
Provides-Extra: dev
Provides-Extra: test
